PythonZhinengXiangmuChuyi/README.md
PythonZhinengXiangmuChuyi/__init__.py
PythonZhinengXiangmuChuyi/__main__.py
PythonZhinengXiangmuChuyi/file.epub
PythonZhinengXiangmuChuyi/index.html
PythonZhinengXiangmuChuyi/css/__init__.py
PythonZhinengXiangmuChuyi/css/annotations.css
PythonZhinengXiangmuChuyi/css/main.css
PythonZhinengXiangmuChuyi/css/normalize.css
PythonZhinengXiangmuChuyi/css/popup.css
PythonZhinengXiangmuChuyi/font/__init__.py
PythonZhinengXiangmuChuyi/font/fontello.eot
PythonZhinengXiangmuChuyi/font/fontello.svg
PythonZhinengXiangmuChuyi/font/fontello.ttf
PythonZhinengXiangmuChuyi/font/fontello.woff
PythonZhinengXiangmuChuyi/img/__init__.py
PythonZhinengXiangmuChuyi/img/annotator-glyph-sprite.png
PythonZhinengXiangmuChuyi/img/annotator-icon-sprite.png
PythonZhinengXiangmuChuyi/img/apple-touch-icon.png
PythonZhinengXiangmuChuyi/img/cancelfullscreen.png
PythonZhinengXiangmuChuyi/img/close.png
PythonZhinengXiangmuChuyi/img/fullscreen.png
PythonZhinengXiangmuChuyi/img/loader.gif
PythonZhinengXiangmuChuyi/img/menu-icon.png
PythonZhinengXiangmuChuyi/img/save.png
PythonZhinengXiangmuChuyi/img/saved.png
PythonZhinengXiangmuChuyi/img/settings-s.png
PythonZhinengXiangmuChuyi/img/settings.png
PythonZhinengXiangmuChuyi/img/star.png
PythonZhinengXiangmuChuyi/js/__init__.py
PythonZhinengXiangmuChuyi/js/epub.js
PythonZhinengXiangmuChuyi/js/epub.min.js
PythonZhinengXiangmuChuyi/js/epub.min.map
PythonZhinengXiangmuChuyi/js/hooks.min.js
PythonZhinengXiangmuChuyi/js/hooks.min.map
PythonZhinengXiangmuChuyi/js/reader.js
PythonZhinengXiangmuChuyi/js/reader.js.map
PythonZhinengXiangmuChuyi/js/reader.min.js
PythonZhinengXiangmuChuyi/js/reader.min.map
PythonZhinengXiangmuChuyi/js/hooks/__init__.py
PythonZhinengXiangmuChuyi/js/hooks/extensions/__init__.py
PythonZhinengXiangmuChuyi/js/hooks/extensions/highlight.js
PythonZhinengXiangmuChuyi/js/libs/__init__.py
PythonZhinengXiangmuChuyi/js/libs/jquery.min.js
PythonZhinengXiangmuChuyi/js/libs/localforage.min.js
python_zhineng_xiangmu_chuyi-2024.3.6.0.dist-info/METADATA
python_zhineng_xiangmu_chuyi-2024.3.6.0.dist-info/WHEEL
python_zhineng_xiangmu_chuyi-2024.3.6.0.dist-info/entry_points.txt
python_zhineng_xiangmu_chuyi-2024.3.6.0.dist-info/top_level.txt
python_zhineng_xiangmu_chuyi-2024.3.6.0.dist-info/RECORD
